dwca/__init__.py
dwca/base/__init__.py
dwca/base/darwincore.py
dwca/base/darwincore_archive.py
dwca/base/simple_darwincore.py
dwca/classes/__init__.py
dwca/classes/chronometric_age.py
dwca/classes/data_file.py
dwca/classes/distribution.py
dwca/classes/event.py
dwca/classes/geological_context.py
dwca/classes/identification.py
dwca/classes/location.py
dwca/classes/material_entity.py
dwca/classes/material_sample.py
dwca/classes/measurement_or_fact.py
dwca/classes/occurrence.py
dwca/classes/organism.py
dwca/classes/outside_class.py
dwca/classes/resource_relationship.py
dwca/classes/species_profile.py
dwca/classes/taxon.py
dwca/terms/__init__.py
dwca/terms/chronometric_age.py
dwca/terms/distribution.py
dwca/terms/event.py
dwca/terms/field.py
dwca/terms/geological_context.py
dwca/terms/identification.py
dwca/terms/location.py
dwca/terms/material_entity.py
dwca/terms/material_sample.py
dwca/terms/measurement_or_fact.py
dwca/terms/occurrence.py
dwca/terms/organism.py
dwca/terms/outside_term.py
dwca/terms/record_level.py
dwca/terms/resource_relationship.py
dwca/terms/species_profile.py
dwca/terms/taxon.py
eml/__init__.py
eml/base/__init__.py
eml/base/eml.py
eml/base/metadata.py
eml/base/version.py
eml/resources/__init__.py
eml/resources/citation.py
eml/resources/dataset.py
eml/resources/keyword_set.py
eml/resources/licence.py
eml/resources/protocol.py
eml/resources/resource.py
eml/resources/resources.py
eml/resources/software.py
eml/resources/coverage/__init__.py
eml/resources/coverage/coverage.py
eml/resources/coverage/geo_coverage.py
eml/resources/coverage/taxa_coverage.py
eml/resources/coverage/time_coverage.py
eml/resources/distribution/__init__.py
eml/resources/distribution/distribution.py
eml/resources/distribution/inline.py
eml/resources/distribution/offline.py
eml/resources/distribution/online.py
eml/types/__init__.py
eml/types/access_type.py
eml/types/address.py
eml/types/change_history.py
eml/types/eml_object.py
eml/types/extension_string.py
pydwca-0.5.1.dist-info/METADATA
pydwca-0.5.1.dist-info/WHEEL
pydwca-0.5.1.dist-info/licenses/LICENSE
pydwca-0.5.1.dist-info/RECORD
