Metadata-Version: 2.4
Name: pydwca
Version: 0.5.1
Summary: Python library to read, parse and write Darwin Core Archive files
Project-URL: Documentation, https://pydwca.readthedocs.io/en/latest/index.html
Project-URL: Issues, https://github.com/IEB-BIODATA/pydwca/issues
Project-URL: Source, https://github.com/IEB-BIODATA/pydwca
Author-email: Juan Saez Hidalgo <jmsaez@ieb-chile.cl>
License-Expression: MPL-2.0
License-File: LICENSE
Classifier: Development Status :: 4 - Beta
Classifier: License :: OSI Approved :: Mozilla Public License 2.0 (MPL 2.0)
Classifier: Programming Language :: Python
Classifier: Programming Language :: Python :: 3.8
Classifier: Programming Language :: Python :: 3.9
Classifier: Programming Language :: Python :: 3.10
Classifier: Programming Language :: Python :: 3.11
Classifier: Programming Language :: Python :: 3.12
Classifier: Programming Language :: Python :: Implementation :: CPython
Classifier: Programming Language :: Python :: Implementation :: PyPy
Requires-Python: >=3.8
Requires-Dist: datetime-interval>=0.2
Requires-Dist: lxml>=5.1.0
Provides-Extra: data
Requires-Dist: pandas; extra == 'data'
Requires-Dist: polars; extra == 'data'
Requires-Dist: rapidfuzz; extra == 'data'
Provides-Extra: full
Requires-Dist: pandas; extra == 'full'
Requires-Dist: polars; extra == 'full'
Requires-Dist: rapidfuzz; extra == 'full'
Requires-Dist: tqdm; extra == 'full'
Provides-Extra: ui
Requires-Dist: pandas; extra == 'ui'
Requires-Dist: tqdm; extra == 'ui'
